[
    {
        "name": "Jagrati Gupta",
        "title": "lorem pusham hsshghsgsgsg.",
        "replies": [
            {
                "name": "Jagrati Gupta",
                "title": "lorem pusham hsshghsgsgsg.",
                "replies": []
            },
            {
                "name": "Jagrati Gupta",
                "title": "lorem pusham hsshghsgsgsg.",
                "replies": []
            },
            {
                "name": "Jagrati Gupta",
                "title": "lorem pusham hsshghsgsgsg.",
                "replies": []
            }
        ]
    },
    {
        "name": "Jagrati Gupta",
        "title": "lorem pusham hsshghsgsgsg.",
        "replies": []
    },
    {
        "name": "Jagrati Gupta",
        "title": "lorem pusham hsshghsgsgsg.",
        "replies": [
            {
                "name": "Jagrati Gupta",
                "title": "lorem pusham hsshghsgsgsg.",
                "replies": [
                    {
                        "name": "Jagrati Gupta",
                        "title": "lorem pusham hsshghsgsgsg.",
                        "replies": []
                    },
                    {
                        "name": "Jagrati Gupta",
                        "title": "lorem pusham hsshghsgsgsg.",
                        "replies": []
                    },
                    {
                        "name": "Jagrati Gupta",
                        "title": "lorem pusham hsshghsgsgsg.",
                        "replies": []
                    }
                ]
            },
            {
                "name": "Jagrati Gupta",
                "title": "lorem pusham hsshghsgsgsg.",
                "replies": []
            },
            {
                "name": "Jagrati Gupta",
                "title": "lorem pusham hsshghsgsgsg.",
                "replies": []
            }
        ]
    },
    {
        "name": "Jagrati Gupta",
        "title": "lorem pusham hsshghsgsgsg.",
        "replies": []
    },
    {
        "name": "Jagrati Gupta",
        "title": "lorem pusham hsshghsgsgsg.",
        "replies": []
    }
]